fockspy
