Metadata-Version: 2.1
Name: fockspy
Version: 0.1.6
Summary: Python module for making calculations connected with open quantum systems
Home-page: UNKNOWN
Author-email: gfaberlane@gmail.com
License: UNKNOWN
Platform: UNKNOWN
